HTTPCompare/__init__.py
HTTPCompare/compare_diff.py
HTTPCompare/compare_keywords.py
HTTPCompare/compare_requests.py
HTTPCompare/data_manager.py
HTTPCompare/json_merge.py
HTTPCompare/jsoncompare.py
HTTPCompare/jsonpath.py
HTTPCompare/libcommons.py
HTTPCompare/version.py
robotframework_httpcompare-1.0.dist-info/LICENSE
robotframework_httpcompare-1.0.dist-info/METADATA
robotframework_httpcompare-1.0.dist-info/WHEEL
robotframework_httpcompare-1.0.dist-info/top_level.txt
robotframework_httpcompare-1.0.dist-info/RECORD
