Metadata-Version: 2.1
Name: robotframework-httpcompare
Version: 1.0
Summary: A generic library to compare two HTTP Requests using Robot Framework
Home-page: https://github.com/dchourasia/httpCompare
Author: Deepak Chourasia
Author-email: deepak.chourasia@gmail.com
License: UNKNOWN
Project-URL: Bug Tracker, https://github.com/dchourasia/httpCompare
Platform: UNKNOWN
Classifier: Programming Language :: Python :: 3
Classifier: License :: OSI Approved :: Apache Software License
Classifier: Intended Audience :: Developers
Classifier: Natural Language :: English
Classifier: Topic :: Software Development :: Testing
Classifier: Development Status :: 5 - Production/Stable
Classifier: Framework :: Robot Framework
Requires-Python: >=3.6
License-File: LICENSE
